docs/Makefile
docs/changelog.rst
docs/cli.rst
docs/conf.py
docs/index.rst
docs/library.rst
docs/requirements.txt
oc4idskit/__init__.py
oc4idskit/__main__.py
oc4idskit/combine.py
oc4idskit/exceptions.py
oc4idskit/transforms.py
oc4idskit/util.py
oc4idskit/commands/__init__.py
oc4idskit/commands/base.py
oc4idskit/commands/combine_project_packages.py
oc4idskit/commands/convert_from_ocds.py
oc4idskit/commands/split_project_packages.py
oc4idskit-0.0.4.dist-info/LICENSE
oc4idskit-0.0.4.dist-info/METADATA
oc4idskit-0.0.4.dist-info/WHEEL
oc4idskit-0.0.4.dist-info/entry_points.txt
oc4idskit-0.0.4.dist-info/top_level.txt
oc4idskit-0.0.4.dist-info/RECORD
