Metadata-Version: 2.1
Name: oc4idskit
Version: 0.0.4
Summary: A suite of command-line tools for working with OC4IDS data
Author-email: Open Contracting Partnership <data@open-contracting.org>
License: BSD
Project-URL: Homepage, https://github.com/open-contracting/oc4idskit
Classifier: License :: OSI Approved :: BSD License
Classifier: Operating System :: OS Independent
Classifier: Programming Language :: Python :: 3.9
Classifier: Programming Language :: Python :: 3.10
Classifier: Programming Language :: Python :: 3.11
Classifier: Programming Language :: Python :: 3.12
Classifier: Programming Language :: Python :: Implementation :: CPython
Classifier: Programming Language :: Python :: Implementation :: PyPy
License-File: LICENSE
Requires-Dist: jsonpointer
Requires-Dist: ocdskit >=1.1.2
Requires-Dist: ocdsmerge >=0.6
Provides-Extra: test
Requires-Dist: coverage ; extra == 'test'
Requires-Dist: pytest ; extra == 'test'
